netflix_spectator_py-1.1.2.dist-info/licenses/LICENSE
spectator/__init__.py
spectator/clock.py
spectator/common_tags.py
spectator/config.py
spectator/protocol_parser.py
spectator/py.typed
spectator/registry.py
spectator/stopwatch.py
spectator/meter/__init__.py
spectator/meter/age_gauge.py
spectator/meter/counter.py
spectator/meter/dist_summary.py
spectator/meter/gauge.py
spectator/meter/max_gauge.py
spectator/meter/meter_id.py
spectator/meter/monotonic_counter.py
spectator/meter/monotonic_counter_uint.py
spectator/meter/percentile_dist_summary.py
spectator/meter/percentile_timer.py
spectator/meter/timer.py
spectator/writer/__init__.py
spectator/writer/file_writer.py
spectator/writer/line_buffer.py
spectator/writer/memory_writer.py
spectator/writer/new_writer.py
spectator/writer/noop_writer.py
spectator/writer/socket_writer.py
netflix_spectator_py-1.1.2.dist-info/METADATA
netflix_spectator_py-1.1.2.dist-info/WHEEL
netflix_spectator_py-1.1.2.dist-info/top_level.txt
netflix_spectator_py-1.1.2.dist-info/RECORD
